<?xml version="1.0" encoding="UTF-8" standalone="no" ?>
<el:level xmlns:xsi="http://www.w3.org/2001/XMLSchema-instance" xsi:schemaLocation="http://enigma-game.org/schema/level/1 level.xsd" xmlns:el="http://enigma-game.org/schema/level/1">
  <el:protected>
    <el:info el:type="level">
      <el:identity el:title="Forget Me Not" el:subtitle="" el:id="hadas04"/>
      <el:version el:score="1" el:release="1" el:revision="1" el:status="stable"/>
      <el:author el:name="Daniel Hadas" el:email="" el:homepage=""/>
      <el:copyright>Copyright © 2010 Daniel Hadas</el:copyright>
      <el:license el:type="GPL v2.0 or above" el:open="true"/>
      <el:compatibility el:enigma="1.10"/>
      <el:modes el:easy="false" el:single="true" el:network="false"/>
      <el:score el:easy="-" el:difficult="-"/>
    </el:info>
    <el:luamain><![CDATA[
ti["-"] = {"fl_sahara"}
ti["~"] = {"fl_water"}
ti[">"] = ti["~"] .. {"st_boulder", orientation=EAST}
ti["<"] = ti["~"] .. {"st_boulder", orientation=WEST}
ti["m"] = {"it_magicwand"}
ti["O"] = ti["~"] .. {"st_oxyd", flavor="c"}
ti["B"] = {"#ac_marble", 0.5, 0}

wo(ti, "-", {
    "~~~~~~~~~~~~~~~~~~~~~~~~~~~~~~~~~~~~~~~~~~~~~~~~~~~~~~~~~~",
    "~~~~~~~~~~~~~~~~~~~~------------------~~~~~~~~~~~~~~~~~~~~",
    "~~~~~~~~~~~~~~~~~~~~-~~~~~------~~~~~-~~~~~~~~~~~~~~~~~~~~",
    "~~~~~~~~~~~~~~~~~~>~-<~O~>--m---<~O~>-~<~~~~~~~~~~~~~~~~~~",
    "~~~~~~~~~~~~~~~~~~>~-<~O~>------<~O~>-~<~~~~~~~~~~~~~~~~~~",
    "~~~~~~~~~~~~~~~~~~>~-<~O~>------<~O~>-~<~~~~~~~~~~~~~~~~~~",
    "~~~~~~~~~~~~~~~~~~>~-<~O~~--B---~~O~>-~<~~~~~~~~~~~~~~~~~~",
    "~~~~~~~~~~~~~~~~~~>~-<~O~>------<~O~>-~<~~~~~~~~~~~~~~~~~~",
    "~~~~~~~~~~~~~~~~~~>~-<~O~>------<~O~>-~<~~~~~~~~~~~~~~~~~~",
    "~~~~~~~~~~~~~~~~~~>~-<~O~>------<~O~>-~<~~~~~~~~~~~~~~~~~~",
    "~~~~~~~~~~~~~~~~~~~~-~~~~~------~~~~~-~~~~~~~~~~~~~~~~~~~~",
    "~~~~~~~~~~~~~~~~~~~~------------------~~~~~~~~~~~~~~~~~~~~",
    "~~~~~~~~~~~~~~~~~~~~~~~~~~~~~~~~~~~~~~~~~~~~~~~~~~~~~~~~~~"})

wo:shuffleOxyd()

 ]]></el:luamain>
    <el:i18n>
      <el:string el:key="title">
        <el:english el:translate="false"/>      
      </el:string>
    </el:i18n>
  </el:protected>
</el:level>
