<?xml version="1.0" encoding="UTF-8" standalone="no" ?>
<el:level xmlns:xsi="http://www.w3.org/2001/XMLSchema-instance" xsi:schemaLocation="http://enigma-game.org/schema/level/1 level.xsd" xmlns:el="http://enigma-game.org/schema/level/1">
  <el:protected>
    <el:info el:type="library">
      <el:identity el:title="" el:id="lib/libmath"/>
      <el:version el:score="1" el:release="1" el:revision="4" el:status="released"/>
      <el:author  el:name="Enigma Team" el:email="" el:homepage=""/>
      <el:copyright>Copyright © 2007, 2008 Enigma Team</el:copyright>
      <el:license el:type="GPL v2.0 or above" el:open="true"/>
      <el:compatibility el:enigma="1.10">
        <el:dependency el:path="lib/liblua" el:id="lib/liblua" el:release="1" el:preload="true"/>
      </el:compatibility>
      <el:modes el:easy="false" el:single="false" el:network="false"/>
      <el:comments>
      </el:comments>
      <el:score el:easy="-" el:difficult="-"/>
    </el:info>
    <el:luamain><![CDATA[

---------------------------------------------------------------------
-- libmath includes mathematical and functions and algorithms
-- of various origins.
---------------------------------------------------------------------
--
-- libmath provides the following functions:
--   lib.math.manhattan_distance(x1, y1, x2, y2)
--   lib.math.digits(number, base)
--   lib.math.combinations(depth, digits)
--   lib.math.cubic_polynomial(a, x, y)
--   lib.math.permutation(n)
--   lib.math.cyclic_permutation(n)  
--   lib.math.random_vector(number, ...)
-- Additional mathematically relevant functions are part of liblua:
--   lib.lua.mod(value, modul)
--   lib.lua.cond(condition, iftrue, iffalse)
--
-- libmath depends on liblua, as lib.math.combinations makes
-- use of lib.lua.deep_copy.
--

lib.math = {}
setmetatable(lib.math, getmetatable(lib))

---------------------------------------------------------------------
--  ADVANCED  POSITION  HANDLING  AND  CALCULATIONS
---------------------------------------------------------------------

-- manhattan_distance calculates the Manhattan-distance between
-- (X1,Y1) and (X2, Y2), which is |X1 - X2| + |Y1 - Y2|.
-- If X2 and Y2 are nil, X1 and Y1 are assumed to be positions
-- instead of coordinates.
function lib.math.manhattan_distance(x1, y1, x2, y2)
  if x1 and y1 and x2 and y2 then
    -- x1, y1, x2, y2 are coordinates
    return math.abs(x1 - x2) + math.abs(y1 - y2)
  end
  if x1 and y1 then
    -- x1 and y1 are positions, possibly tables.
    local p1 = x1
    local p2 = y1
    if type(p1) == "table" then
      p1 = po(p1)
    end
    if type(p2) == "table" then
      p2 = po(p2)
    end
    return math.abs(p1.x - p2.x) + math.abs(p1.y - p2.y)
  end
  error("manhattan_distance: Too less arguments.", 2)
end

---------------------------------------------------------------------
--  MATHEMATICAL  FUNCTIONS
---------------------------------------------------------------------

-- digits returns a table whose elements are the digits of NUMBER
-- in base BASE. BASE can be a number (e.g. 3 to get ternary)
-- as well as a table (then the table entries with numerical
-- keys will be used as digits).
-- Examples:
--   lib.math.digits(13, 2) = {1, 0, 1, 1}
--   lib.math.digits(15, 16) = {15}
--   lib.math.digits(17, 3) = {2, 2, 1}
--   lib.math.digits(17, {2, "b", 5}) = {5, 5, "b"}
-- Hexadecimal would be:
--   lib.math.digits(x, {0,1,2,3,4,5,6,7,8,9,"A","B","C","D","E","F"})
-- NUMBER is supposed to be a non-negative integer.
function lib.math.digits(number, base)
  -- Check arguments and calculate fullbase and exponent
  if type(number) ~= "number" then
    error("digits: First argument not a number ("..type(number).." instead).", 2)
  end
  if (type(base) ~= "number") and (type(base) ~= "table") then
    error("digits: Second argument not valid type ("..type(base)..").", 2)
  end
  if (number < 0) or (number ~= math.ceil(number)) then
    error("digits: First argument out of range ("..number..").", 2)
  end
  local fullbase = {}
  local exponent = 0
  if type(base) == "number" then
    if (base < 2) or (base ~= math.ceil(base)) then
      error("digits: Second argument out of range ("..base..").", 2)
    end
    for j = 1, base do
      table.insert(fullbase, j - 1)
    end
  else -- type(base) == "table"
    if table.getn(base) < 2 then
      error("digits: Second argument has not enough elements.", 2)
    end
    fullbase = base
  end
  exponent = table.getn(fullbase)
  -- Decompose NUMBER
  local remains = number
  local result = {}
  while remains > 0 do
    local d = remains % exponent
    table.insert(result, fullbase[d + 1])
    remains = (remains - d) / exponent
    if remains ~= math.ceil(remains) then
      error("digits: Internal error during calculation (remains = "..remains..").", 2)
    end
  end
  return result
end

-- Return a table of all combinations of DEPTH entries,
-- each of which is chosen from DIGITS.
-- Example: lib.math.combinations(3, {7, 8, "a"}) will return
--   { {7,7,7}, {7,7,8}, {7,7,"a"}, {7,8,7}, {7,8,8}, {7,8,"a"},
--     {7,"a",7}, {7,"a",8}, {7,"a","a"}, {8,7,7}, ... }
-- Mathematically, it builds the leafs of an #DIGITS-ary tree
-- of depth DEPTH. Note that liblua has to be loaded to use
-- lib.math.combinations.
function lib.math.combinations(depth, digits)
  local all_combinations = {{}}
  local digs = digits
  if (type(depth) ~= "number") or (depth < 1) or (depth ~= math.floor(depth)) then
    error("combinations: First argument (depth) not a number or out of range.", 2)
  end
  if type(digits) == "number" then
    if (digits < 1) or (digits ~= math.floor(digits)) then
      error("combinations: Second argument (digits) out of range.", 2)
    end
    digs = {}
    for j = 1, digits do
      digs[j] = j
    end
  end
  if type(digs) ~= "table" then
    error("combinations: Second argument (digits) should be number or table.", 2)
  end
  for _ = 1, depth do
    local next_step = {}
    for _, old_combination in pairs(all_combinations) do
      for _, new_digit in pairs(digs) do
        local new_combination = lib.lua.deep_copy(old_combination)
        table.insert(new_combination, new_digit)
        table.insert(next_step, new_combination)
      end
    end
    all_combinations = next_step
  end
  return all_combinations
end

-- cubic_polynomial returns the result of the
-- following polynomial with coefficients in A:
-- a[10]*y*y*y + a[9]*x*y*y + a[8]*x*x*y + a[7]*x*x*x
--   + a[6]*y*y + a[5]*x*y + a[4]*x*x + a[3]*y + a[2]*x + a[1]
-- You can use lib.math.random_vector(10, ...) and
-- a modulo operation to easily form a random
-- pattern of a floor, or choose the coefficients
-- to your own liking. Entries in A which are not
-- numbers are considered zero.
function lib.math.cubic_polynomial(a, x, y)
  if type(a) ~= "table" then
    error("cubic_polynomial: First argument not a table (" .. type(a)
          .. " instead).", 2)
  end
  if (type(x) ~= "number") or (type(y) ~= "number") then
    error("cubic_polynomial: Second or third argument not a number.", 2)
  end
  return   (a[10] or 0)*y*y*y + (a[9] or 0)*x*y*y + (a[8] or 0)*x*x*y
         + (a[7] or 0)*x*x*x + (a[6] or 0)*y*y + (a[5] or 0)*x*y
         + (a[4] or 0)*x*x + (a[3] or 0)*y + (a[2] or 0)*x + (a[1] or 0)
end

-- steps takes DISCRIMINATOR and returns a value dependend on where
-- in the table STEPS of integers the discriminator is located.
-- Example: lib.math.steps(x, {4, 8, 13}) returns:
--     0: If        x < 4
--     1: If   4 <= x < 8
--     2: If   8 <= x < 13
--     3: If  13 <= x
-- Negative and non-integer values are allowed.
function lib.math.steps(discriminator, steps)
  if type(discriminator) ~= "number" then
    error("lib.math.steps: First argument is " .. type(discriminator)
        .. "/" .. usertype(discriminator) .. ", should be number.", 2)
  end
  if type(steps) ~= "table" then
    error("lib.math.steps: Second argument is " .. type(discriminator)
        .. "/" .. usertype(discriminator) .. ", should be table.", 2)
  end
  local result = 0
  for _, height in ipairs(steps) do
    if type(height) ~= "number" then
      error("lib.math.steps: " .. type(discriminator) .. "/" .. usertype(discriminator)
          .. " in table of second argument, should be number.", 2)
    end
    if discriminator < height then
      return result
    else
      result = result + 1
    end
  end
  return result
end

---------------------------------------------------------------------
--  PERMUTATIONS  AND  RANDOM  NUMBERS
---------------------------------------------------------------------

-- Return a random permutation of n elements.
-- This function outputs a table with integer entries between
-- 1 and n at positions 1 to n.
function lib.math.permutation(n)
  if type(n) ~= "number" then
    error("permutation: Expected number, got "..type(n).."!", 2)
  end
  if (n < 1) or (n ~= math.floor(n)) then
    error("permutation: Argument must be positive integer.", 2)
  end
  if n == 1 then
    return {1}
  end
  local sequence = {}
  for j = 1, n do
    table.insert(sequence, j)
  end
  for n = table.getn(sequence), 2, -1 do
    local m = math.random(n)
    sequence[n], sequence[m] = sequence[m], sequence[n]
  end
  return sequence
end

-- Return a random cyclic permutation (i.e. with only one cycle) of n elements.
function lib.math.cyclic_permutation(n)  
  if type(n) ~= "number" then
    error("cyclic_permutation: Expected number, got "..type(n).."!", 2)
  end
  local sequence1 = lib.math.permutation(n)
  local sequence2 = {}
  for j = 1, n - 1 do
    sequence2[sequence1[j]] = sequence1[j+1]
  end
  sequence2[sequence1[n]] = sequence1[1]
  return sequence2
end

-- Return a table with NUMBER random entries.
-- Additional arguments like with math.random.
function lib.math.random_vector(number, ...)
  if type(number) ~= "number" then
    error("random_vector: First argument not a number ("..type(number).." instead).", 2)
  end
  if (number < 0) or (number ~= math.ceil(number)) then
    error("random_vector: First argument out of range ("..number..").", 2)
  end
  local result = {}
  for j = 1, number do
    result[j] = math.random(...)
  end
  return result
end

    ]]></el:luamain>
    <el:i18n>
    </el:i18n>
  </el:protected>
</el:level>

